libopencor-0.20251204.0.dist-info/RECORD
libopencor-0.20251204.0.dist-info/WHEEL
libopencor-0.20251204.0.dist-info/top_level.txt
libopencor-0.20251204.0.dist-info/METADATA
libopencor-0.20251204.0.dist-info/licenses/LICENSE.txt
libopencor/module.abi3.so
libopencor/__init__.py
